sprite_detection_tool/__init__.py
sprite_detection_tool/spriteutil.py
sprite_detection_tool-3.2.7.dist-info/LICENSE
sprite_detection_tool-3.2.7.dist-info/METADATA
sprite_detection_tool-3.2.7.dist-info/WHEEL
sprite_detection_tool-3.2.7.dist-info/top_level.txt
sprite_detection_tool-3.2.7.dist-info/RECORD
