Metadata-Version: 2.1
Name: sprite-detection-tool
Version: 3.2.7
Summary: An useful detect sprite of image package
Home-page: https://github.com/intek-training-jsc/sprite-detection-lhoaibao/tree/master
Author: lhoaibao
Author-email: lehoaibao081999@gmail.com
License: UNKNOWN
Platform: UNKNOWN
Classifier: Programming Language :: Python :: 3
Classifier: License :: OSI Approved :: MIT License
Classifier: Operating System :: OS Independent
Requires-Python: >=3.6
Requires-Dist: setuptools
Requires-Dist: wheel
Requires-Dist: twine
Requires-Dist: pipfile
Requires-Dist: pillow
Requires-Dist: numpy
